{
	"configurations" : 
	[
		{
			"directories" : 
			[
				{
					"build" : ".",
					"jsonFile" : "directory-.-Debug-f5ebdc15457944623624.json",
					"minimumCMakeVersion" : 
					{
						"string" : "3.18.1"
					},
					"projectIndex" : 0,
					"source" : ".",
					"targetIndexes" : 
					[
						0,
						1
					]
				}
			],
			"name" : "Debug",
			"projects" : 
			[
				{
					"directoryIndexes" : 
					[
						0
					],
					"name" : "vaEnc",
					"targetIndexes" : 
					[
						0,
						1
					]
				}
			],
			"targets" : 
			[
				{
					"directoryIndex" : 0,
					"id" : "Enc::@6890427a1f51a3e7e1df",
					"jsonFile" : "target-Enc-Debug-69e7c2efe65874ebe109.json",
					"name" : "Enc",
					"projectIndex" : 0
				},
				{
					"directoryIndex" : 0,
					"id" : "Query::@6890427a1f51a3e7e1df",
					"jsonFile" : "target-Query-Debug-4ad2f9a789f827d631f6.json",
					"name" : "Query",
					"projectIndex" : 0
				}
			]
		}
	],
	"kind" : "codemodel",
	"paths" : 
	{
		"build" : "/run/media/ethanw/LinuxGames/Repos/enc/VAAPI/build",
		"source" : "/run/media/ethanw/LinuxGames/Repos/enc/VAAPI"
	},
	"version" : 
	{
		"major" : 2,
		"minor" : 5
	}
}
